[
  {
    "name": "Robert Downey",
    "profile_pic": "assets/images/user.png",
    "bio": "bio here",
    "restaurant": "Rob's Ribs"
  },
  {
    "name": "Robert Downey",
    "profile_pic": "assets/images/user.png",
    "bio": "bio here",
    "restaurant": "Rob's Ribs"
  }
  {
    "name": "Robert Downey",
    "profile_pic": "assets/images/user.png",
    "bio": "bio here",
    "restaurant": "Rob's Ribs"
  }
  {
    "name": "Robert Downey",
    "profile_pic": "assets/images/user.png",
    "bio": "bio here",
    "restaurant": "Rob's Ribs"
  }
  {
    "name": "Robert Downey",
    "profile_pic": "assets/images/user.png",
    "bio": "bio here",
    "restaurant": "Rob's Ribs"
  }
]
